aws_mcp_server/__init__.py
aws_mcp_server-0.0.0.dist-info/METADATA
aws_mcp_server-0.0.0.dist-info/WHEEL
aws_mcp_server-0.0.0.dist-info/top_level.txt
aws_mcp_server-0.0.0.dist-info/RECORD
